cli_result/__init__.py
cli_result/core.py
cli_result/parser_test.py
cli_result/version.py
cli_result-0.3.4.dist-info/LICENSE
cli_result-0.3.4.dist-info/METADATA
cli_result-0.3.4.dist-info/WHEEL
cli_result-0.3.4.dist-info/top_level.txt
cli_result-0.3.4.dist-info/RECORD
